vtpl/__init__.py
vtpl/vtpl_api_wrapper.py
vtpl/vtpl_video_stream.py
vtpl_api_wrapper-1.0.6.dist-info/LICENSE
vtpl_api_wrapper-1.0.6.dist-info/METADATA
vtpl_api_wrapper-1.0.6.dist-info/WHEEL
vtpl_api_wrapper-1.0.6.dist-info/top_level.txt
vtpl_api_wrapper-1.0.6.dist-info/RECORD
